cdxj_indexer/__init__.py
cdxj_indexer/amf.py
cdxj_indexer/bufferiter.py
cdxj_indexer/main.py
cdxj_indexer/postquery.py
cdxj_indexer-1.4.6.dist-info/LICENSE
cdxj_indexer-1.4.6.dist-info/METADATA
cdxj_indexer-1.4.6.dist-info/WHEEL
cdxj_indexer-1.4.6.dist-info/entry_points.txt
cdxj_indexer-1.4.6.dist-info/top_level.txt
cdxj_indexer-1.4.6.dist-info/zip-safe
cdxj_indexer-1.4.6.dist-info/RECORD
