Metadata-Version: 2.1
Name: cdxj_indexer
Version: 1.4.6
Summary: CDXJ Indexer for WARC and ARC files
Home-page: https://github.com/webrecorder/cdxj-indexer
Author: Ilya Kreymer
Author-email: ikreymer@gmail.com
License: Apache 2.0
Classifier: Development Status :: 4 - Beta
Classifier: Environment :: Web Environment
Classifier: License :: OSI Approved :: Apache Software License
Classifier: Programming Language :: Python :: 3
Classifier: Programming Language :: Python :: 3.5
Classifier: Programming Language :: Python :: 3.6
Classifier: Programming Language :: Python :: 3.7
Classifier: Programming Language :: Python :: 3.8
Classifier: Topic :: Software Development :: Libraries :: Python Modules
Classifier: Topic :: Utilities
Provides: cdxj_indexer
License-File: LICENSE
Requires-Dist: warcio
Requires-Dist: surt
Requires-Dist: idna<3.0
Requires-Dist: py3amf
Requires-Dist: multipart
